README.md
setup.py
word_treasure/__init__.py
word_treasure/test_wordt.py
word_treasure/word_treasure.py
word_treasure.egg-info/PKG-INFO
word_treasure.egg-info/SOURCES.txt
word_treasure.egg-info/dependency_links.txt
word_treasure.egg-info/entry_points.txt
word_treasure.egg-info/not-zip-safe
word_treasure.egg-info/top_level.txt
word_treasure/wordnik/AccountApi.py
word_treasure/wordnik/WordApi.py
word_treasure/wordnik/WordListApi.py
word_treasure/wordnik/WordListsApi.py
word_treasure/wordnik/WordsApi.py
word_treasure/wordnik/__init__.py
word_treasure/wordnik/swagger.py
word_treasure/wordnik/models/ApiTokenStatus.py
word_treasure/wordnik/models/AudioFile.py
word_treasure/wordnik/models/AuthenticationToken.py
word_treasure/wordnik/models/Bigram.py
word_treasure/wordnik/models/Citation.py
word_treasure/wordnik/models/ContentProvider.py
word_treasure/wordnik/models/Definition.py
word_treasure/wordnik/models/DefinitionSearchResults.py
word_treasure/wordnik/models/Example.py
word_treasure/wordnik/models/ExampleSearchResults.py
word_treasure/wordnik/models/ExampleUsage.py
word_treasure/wordnik/models/Facet.py
word_treasure/wordnik/models/FacetValue.py
word_treasure/wordnik/models/Frequency.py
word_treasure/wordnik/models/FrequencySummary.py
word_treasure/wordnik/models/Label.py
word_treasure/wordnik/models/Note.py
word_treasure/wordnik/models/Related.py
word_treasure/wordnik/models/ScoredWord.py
word_treasure/wordnik/models/ScrabbleScoreResult.py
word_treasure/wordnik/models/Sentence.py
word_treasure/wordnik/models/SimpleDefinition.py
word_treasure/wordnik/models/SimpleExample.py
word_treasure/wordnik/models/StringValue.py
word_treasure/wordnik/models/Syllable.py
word_treasure/wordnik/models/TextPron.py
word_treasure/wordnik/models/User.py
word_treasure/wordnik/models/WordList.py
word_treasure/wordnik/models/WordListWord.py
word_treasure/wordnik/models/WordObject.py
word_treasure/wordnik/models/WordOfTheDay.py
word_treasure/wordnik/models/WordSearchResult.py
word_treasure/wordnik/models/WordSearchResults.py
word_treasure/wordnik/models/__init__.py