Metadata-Version: 1.1
Name: word-treasure
Version: 1.1
Summary: Simple tool to look up words with single command
Home-page: https://github.com/harsimrans/word-treasure
Author: harsimran singh
Author-email: harsimransingh032@gmail.com
License: GNU GPL v3.0
Download-URL: https://github.com/harsimrans/word-treasure/archive/1.1.zip
Platform: UNKNOWN
